<?xml version="1.0" encoding="UTF-8"?>
<Rules generatingVersion="8.3.0.bapollo.r3304.b2032">
    <RuleGroup id="ID0" oid="-1y2p0ij32e8ba:-1y2p0ij323dda" class="rulegroup" name="Splunk App for Tripwire Enterprise v1.0" toplevel="true" externalId="USR.900e51b0-48cc-439b-91ff-930f95c0824a">
        <Description></Description>
        <Children>
            <Child refid="ID1" />
            <Child refid="ID2" />
        </Children>
    </RuleGroup>
    <PosixFileRule id="ID1" oid="-1y2p0ij32e7qm:-1y2p0ij323dd7" class="rule" name="Tripwire Enterprise Running on UNIX" externalId="USR.b874db9a-eb6a-4664-9042-909a2bc46d86">
        <Description>Guaranteed changed file to trigger export actions</Description>
        <Severity>100</Severity>
        <RealTime>false</RealTime>
        <Actions />
        <StartPoints>
            <Start>
                <Target>/usr/local/tripwire/te/server/data/log/teserver.log</Target>
                <Severity>0</Severity>
                <RecurseLevel>0</RecurseLevel>
                <StoreContent>false</StoreContent>
                <Filters>
                    <Filter>
                        <TypeId>1</TypeId>
                    </Filter>
                </Filters>
                <Criteria refid="ID3" />
            </Start>
        </StartPoints>
        <StopPoints />
        <Traverse>true</Traverse>
    </PosixFileRule>
    <Criteria id="ID3" oid="-1y2p0ij32e7qv:-1y2p0ij32e7n4" class="Criteria" name="Unix - Content Only" Genre="com.tripwire.si.core.fs.posix.PosixFileSystemRule">
        <Description></Description>
        <Attributes>
            <ElementType>1</ElementType>
            <Attribute>SHA-1</Attribute>
            <Attribute>Size</Attribute>
        </Attributes>
        <Attributes>
            <ElementType>2</ElementType>
        </Attributes>
    </Criteria>
    <WindowsFileRule id="ID2" oid="-1y2p0ij32e7q2:-1y2p0ij323dcy" class="rule" name="Tripwire Enterprise Running on Windows" externalId="USR.69d20926-6632-4d0e-81fc-ee243dcc70f5">
        <Description>Guaranteed changed file to trigger export actions</Description>
        <Severity>100</Severity>
        <RealTime>false</RealTime>
        <Actions />
        <StartPoints>
            <Start>
                <Target>C:\Program Files\Tripwire\TE\Server\data\log\teserver.log</Target>
                <Severity>0</Severity>
                <RecurseLevel>0</RecurseLevel>
                <StoreContent>false</StoreContent>
                <Filters>
                    <Filter>
                        <TypeId>1</TypeId>
                    </Filter>
                </Filters>
                <Criteria refid="ID4" />
            </Start>
        </StartPoints>
        <StopPoints />
    </WindowsFileRule>
    <Criteria id="ID4" oid="-1y2p0ij32e7qv:-1y2p0ij32e7na" class="Criteria" name="Windows - Content Only" Genre="com.tripwire.si.core.fs.windows.WindowsFileSystemRule">
        <Description></Description>
        <Attributes>
            <ElementType>1</ElementType>
            <Attribute>Stream Count</Attribute>
            <Attribute>SHA-1</Attribute>
            <Attribute>Stream SHA-1</Attribute>
            <Attribute>Size</Attribute>
        </Attributes>
        <Attributes>
            <ElementType>2</ElementType>
            <Attribute>Stream Count</Attribute>
            <Attribute>Stream SHA-1</Attribute>
        </Attributes>
    </Criteria>
</Rules>