<form version="1.1" theme="light">
  <label>Software Diverse Families</label>
  <description>Optimized.</description>
  <fieldset submitButton="false" autoRun="true">
    <input type="dropdown" token="cpyKey" depends="$HideThis$">
      <label>Hidden Customer</label>
      <choice value="0">Default</choice>
      <default>0</default>
      <initialValue>0</initialValue>
    </input>
    <input type="dropdown" token="groupIdSelected" searchWhenChanged="true">
      <label>GROUP</label>
      <search>
        <query>`cisco_oi_index("$cpyKey$")` sourcetype::cisco:bcs:devicegroup
| mvexpand groupName 
| dedup groupName
| table groupName
| sort groupName</query>
        <earliest>-1w@w</earliest>
        <latest>now</latest>
      </search>
      <fieldForLabel>groupName</fieldForLabel>
      <fieldForValue>groupName</fieldForValue>
      <change>
        <condition match="match( value, &quot;_default_&quot;)">
          <set token="groupSelector"></set>
          <set token="singleLineGroupSelector">where 1=1</set>
        </condition>
        <condition>
          <set token="groupSelector">[| tstats values(deviceId) as deviceId WHERE ( `cisco_oi_index($cpyKey$)` sourcetype::cisco:bcs:devicegroupmember groupName="$groupIdSelected$")]</set>
          <set token="singleLineGroupSelector">search [| tstats values(deviceId) as deviceId WHERE ( `cisco_oi_index($cpyKey$)` sourcetype::cisco:bcs:devicegroupmember groupName="$groupIdSelected$")]</set>
        </condition>
      </change>
      <choice value="_default_">No group filtering</choice>
      <default>_default_</default>
      <initialValue>_default_</initialValue>
    </input>
    <input type="time" token="field1">
      <label>Timeframe:</label>
      <default>
        <earliest>-7d@h</earliest>
        <latest>now</latest>
      </default>
    </input>
  </fieldset>
  <row>
    <panel depends="$HideThis$">
      <table>
        <title>Key Tracks CSV search</title>
        <search>
          <finalized>
            <condition match=" 'job.resultCount' != 0">
              <set token="kvLookupFound">$result.lookupFound$</set>
            </condition>
          </finalized>
          <query>| rest/servicesNS/-/-/data/lookup-table-files 
| search eai:appName=custom_insights title="Key_Tracks-$cpyKey$.csv" 
| table title</query>
          <earliest>$field1.earliest$</earliest>
          <latest>$field1.latest$</latest>
        </search>
        <option name="drilldown">none</option>
        <option name="refresh.display">progressbar</option>
      </table>
    </panel>
  </row>
  <row>
    <panel depends="$HideThis$">
      <table>
        <title>Base: Device Software by Product Family</title>
        <search>
          <done>
            <set token="base_device_sw_family_sid">$job.sid$</set>
          </done>
          <query>`cisco_oi_index($cpyKey$)` sourcetype::cisco:bcs:device 
| stats values(deviceName) as deviceName
    by deviceId productFamily softwareVersion productId 
| search productId!=null 
| fields deviceId, deviceName, productId, productFamily, softwareVersion 
| $singleLineGroupSelector$</query>
          <earliest>$field1.earliest$</earliest>
          <latest>$field1.latest$</latest>
        </search>
        <option name="drilldown">none</option>
        <option name="refresh.display">progressbar</option>
      </table>
    </panel>
  </row>
  <row>
    <panel>
      <single>
        <search>
          <query>| stats count as Initialize 
| eval title="Software Diversity - Top 2 Diverse Families"
| table title</query>
          <earliest>-24h@h</earliest>
          <latest>now</latest>
        </search>
        <option name="drilldown">none</option>
        <option name="height">50</option>
        <option name="refresh.display">progressbar</option>
      </single>
    </panel>
  </row>
  <row>
    <panel>
      <title>SW Diversity: Number of Software Verions - Enterprise</title>
      <single>
        <search>
          <query>| loadjob $base_device_sw_family_sid$
| stats dc(softwareVersion) as "SW Versions"</query>
          <earliest>$field1.earliest$</earliest>
          <latest>$field1.latest$</latest>
        </search>
        <option name="drilldown">none</option>
        <option name="height">100</option>
        <option name="rangeColors">["0x53a051","0xf8be34","0xdc4e41"]</option>
        <option name="rangeValues">[30,60]</option>
        <option name="refresh.display">progressbar</option>
        <option name="underLabel">Green &lt; Yellow: 30-60 &lt; Red</option>
        <option name="useColors">1</option>
      </single>
    </panel>
  </row>
  <row>
    <panel>
      <title>Software Versions by Product Family ("Head of the Diversity Snake")</title>
      <chart>
        <title>Deploy standard software versions (either Cisco Recommended, or more prevalent in production) to the Top 2 product families below</title>
        <search>
          <query>| loadjob $base_device_sw_family_sid$
| stats dc(softwareVersion) as "SW Versions" by productFamily 
| table productFamily, "SW Versions" 
| sort -"SW Versions"</query>
          <earliest>$field1.earliest$</earliest>
          <latest>$field1.latest$</latest>
        </search>
        <option name="charting.axisLabelsX.majorLabelStyle.rotation">-45</option>
        <option name="charting.chart">column</option>
        <option name="charting.chart.showDataLabels">all</option>
        <option name="charting.drilldown">none</option>
        <option name="charting.legend.placement">none</option>
        <option name="refresh.display">progressbar</option>
      </chart>
    </panel>
  </row>
  <row>
    <panel>
      <title>Top 2 Diverse Family Devices</title>
      <single>
        <title>Sum of devices in Top 2 Families by # versions</title>
        <search>
          <query>| loadjob $base_device_sw_family_sid$
| eventstats dc(softwareVersion) as VersionsInFamily by productFamily 
| eventstats count as DevicesRunningVersion by productFamily, softwareVersion, VersionsInFamily 
| search VersionsInFamily&gt;=2 AND softwareVersion!="Not Found" 
| fields productFamily, softwareVersion, DevicesRunningVersion, VersionsInFamily 
| dedup productFamily, softwareVersion, DevicesRunningVersion, VersionsInFamily 
| sort -VersionsInFamily, productFamily 
| stats sum(DevicesRunningVersion) as Devices by productFamily, VersionsInFamily 
| sort -VersionsInFamily 
| head 2 
| stats sum(Devices) as Top2devices</query>
          <earliest>$field1.earliest$</earliest>
          <latest>$field1.latest$</latest>
        </search>
        <option name="drilldown">none</option>
        <option name="rangeColors">["0x53a051","0x0877a6","0xf8be34","0xf1813f","0xdc4e41"]</option>
        <option name="refresh.display">progressbar</option>
      </single>
    </panel>
    <panel>
      <title>Diversity Reduction Goal: Top 2 Diverse Families</title>
      <single>
        <title># Versions to Eliminate by Consolidating Top 2 Diverse Families to 4 Versions per Family</title>
        <search>
          <query>| loadjob $base_device_sw_family_sid$
| eventstats dc(softwareVersion) as VersionsInFamily by productFamily 
| eventstats max(VersionsInFamily) as maxVersions 
| eventstats count as DevicesRunningVersion by productFamily, softwareVersion, VersionsInFamily 
| search softwareVersion!="Not Found" 
| table productFamily, DevicesRunningVersion, VersionsInFamily, maxVersions 
| dedup productFamily, VersionsInFamily 
| sort -VersionsInFamily, productFamily
| head 2
| stats sum(VersionsInFamily) as Top2familyVersions
| eval versionsSaved=Top2familyVersions-8
| eval fixedVersionsSaved = if(Top2familyVersions&lt;8, 0, versionsSaved)
| table fixedVersionsSaved</query>
          <earliest>$field1.earliest$</earliest>
          <latest>$field1.latest$</latest>
        </search>
        <option name="drilldown">none</option>
        <option name="refresh.display">progressbar</option>
      </single>
    </panel>
  </row>
  <row>
    <panel>
      <title>Software Diversity Details</title>
      <table>
        <search>
          <query>| loadjob $base_device_sw_family_sid$
| search productFamily!=null AND softwareVersion!="Not Found" 
| dedup deviceId, deviceName, productFamily, softwareVersion 
| eventstats dc(softwareVersion) as VersionsInFamily by productFamily 
| eventstats dc(deviceId) as DevicesInFamily by productFamily 
| eventstats count as DevicesRunningVersion by productFamily, softwareVersion, VersionsInFamily 
| fields productFamily, softwareVersion, DevicesRunningVersion, VersionsInFamily, DevicesInFamily
| dedup productFamily, softwareVersion, DevicesRunningVersion, VersionsInFamily 
| stats sum(DevicesRunningVersion) as Devices by productFamily, softwareVersion, VersionsInFamily, DevicesInFamily
| eval percDevices = round(100*Devices/DevicesInFamily)
| sort percDevices</query>
          <earliest>$field1.earliest$</earliest>
          <latest>$field1.latest$</latest>
        </search>
        <option name="drilldown">none</option>
        <option name="refresh.display">progressbar</option>
      </table>
    </panel>
  </row>
</form>